codegen/__init__.py
codegen/__main__.py
codegen/generator.py
codegen/network.py
codegen/query_presets.py
codegen/src/__init__.py
codegen/src/base_class.py
codegen/src/consts.py
codegen/src/enums.py
codegen/src/extractor.py
codegen/src/printer.py
codegen/src/priority.py
codegen/src/sp_builder.py
codegen/src/sp_schema.py
codegen/src/utils.py
codegen/src/templates/enum_template.py
codegen/src/templates/mutation_template.py
codegen/src/templates/query_template.py
codegen/src/templates/scalar_template.py
codegen/src/templates/simple_type_template.py
codegen/src/templates/type_refs_template.py
codegen/src/templates/type_template.py
py_graphql_mapper-1.1.2.data/data/config.ini
pygqlmap/__init__.py
pygqlmap/components.py
pygqlmap/config.ini
pygqlmap/enums.py
pygqlmap/gql_operations.py
pygqlmap/gql_types.py
pygqlmap/helper.py
pygqlmap/network.py
pygqlmap/src/__init__.py
pygqlmap/src/arg_builtin.py
pygqlmap/src/base.py
pygqlmap/src/builder.py
pygqlmap/src/components.py
pygqlmap/src/consts.py
pygqlmap/src/enums.py
pygqlmap/src/gql_init.py
pygqlmap/src/translator.py
pygqlmap/src/utils.py
py_graphql_mapper-1.1.2.dist-info/LICENSE
py_graphql_mapper-1.1.2.dist-info/METADATA
py_graphql_mapper-1.1.2.dist-info/WHEEL
py_graphql_mapper-1.1.2.dist-info/entry_points.txt
py_graphql_mapper-1.1.2.dist-info/top_level.txt
py_graphql_mapper-1.1.2.dist-info/RECORD
