Metadata-Version: 2.1
Name: py-graphql-mapper
Version: 1.1.2
Summary: A python library to call GraphQL APIs without using hardcoded strings
Home-page: https://github.com/dapalex/py-graphql-mapper/tree/1.1.2
Author: Alex Dap
Author-email: Alex Dap <shlisi2017@gmail.com>
License: MIT License
Project-URL: Homepage, https://github.com/dapalex/py-graphql-mapper/
Project-URL: Source Code, https://github.com/dapalex/py-graphql-mapper/tree/1.1.2
Project-URL: Bug Tracker, https://github.com/dapalex/py-graphql-mapper/issues
Project-URL: Release Notes, https://github.com/dapalex/py-graphql-mapper/tree/1.1.2/RELEASE_NOTES.MD
Keywords: python,graphql,mapping
Classifier: Programming Language :: Python :: 3
Classifier: License :: OSI Approved :: MIT License
Classifier: Operating System :: OS Independent
Requires-Python: >=3.10
License-File: LICENSE
